README.md
rec_spotify/__init__.py
rec_spotify/cli.py
rec_spotify/config.py
rec_spotify/console.py
rec_spotify/database.py
rec_spotify/items.py
rec_spotify/lyrics.py
rec_spotify/manager.py
rec_spotify/messages.py
rec_spotify/recorder.py
rec_spotify/spotify.py
rec_spotify/utils.py
rec_spotify-1.8.1.dist-info/entry_points.txt
rec_spotify-1.8.1.dist-info/METADATA
rec_spotify-1.8.1.dist-info/WHEEL
rec_spotify-1.8.1.dist-info/RECORD
