Metadata-Version: 2.1
Name: rec-spotify
Version: 1.8.1
Summary: 📻 Record and sync Spotify tracks, albums, and playlists.
Home-page: https://github.com/oSeeLight/rec-spotify
License: MIT
Keywords: spotify,record
Author: Jacov Rainz
Author-email: oSeeLight@proton.me
Requires-Python: >=3.11,<4.0
Classifier: License :: OSI Approved :: MIT License
Classifier: Programming Language :: Python :: 3
Classifier: Programming Language :: Python :: 3.11
Requires-Dist: eyed3 (>=0.9.7,<0.10.0)
Requires-Dist: pyaudiowpatch (==0.2.12.6)
Requires-Dist: pydub (==0.25.1)
Requires-Dist: requests (>=2.31.0,<3.0.0)
Requires-Dist: rich (>=13.4.2,<14.0.0)
Requires-Dist: spotipy (>=2.23.0,<3.0.0)
Project-URL: Repository, https://github.com/oSeeLight/rec-spotify
